feni/__init__.py
feni/__main__.py
feni/articles.py
feni/configuration.py
feni/decorator.py
feni/exceptions.py
feni/feni.py
feni/filehandlers.py
feni/preprocessor.py
Feni-1.23.dist-info/METADATA
Feni-1.23.dist-info/WHEEL
Feni-1.23.dist-info/entry_points.txt
Feni-1.23.dist-info/top_level.txt
Feni-1.23.dist-info/RECORD
