Metadata-Version: 2.1
Name: Feni
Version: 1.23
Summary: A simple static site generator.
Home-page: http://bitbucket.org/sras/feni
Author: Sandeep.C.R
Author-email: sandeepcr2@gmail.com
License: MIT
Platform: UNKNOWN
Requires-Dist: bottle
Requires-Dist: lesscpy
Requires-Dist: markdown
Requires-Dist: pyyaml
